Metadata-Version: 2.4
Name: camera2geo
Version: 1.0.2
Summary: Camera to geographic space image conversion
Author-email: Kanoa Lindiwe <cankanoa@gmail.com>
Maintainer-email: Joseph Emile Honour Percival <ipercival@gmail.com>
License: AGPL
Project-URL: Bug Tracker, https://github.com/cankanoa/camera2geo/issues
Project-URL: Source, https://github.com/cankanoa/camera2geo
Keywords: remote sensing,georeferencing,camera projection,coordinate transformation,geographic information systems(gis),QGIS plugin,uas/drone,geospatial,image processing,environmental monitoring
Classifier: Programming Language :: Python :: 3
Classifier: License :: OSI Approved :: GNU Affero General Public License v3 or later (AGPLv3+)
Classifier: Operating System :: OS Independent
Requires-Python: <3.13,>=3.10
License-File: LICENSE
Requires-Dist: rasterio>=1.3.9
Requires-Dist: numpy>=1
Requires-Dist: pyproj>=3.5
Requires-Dist: shapely>=2.0.2
Requires-Dist: pyexiftool
Requires-Dist: pillow>=10.3.0
Requires-Dist: vector3d>=1.1.1
Requires-Dist: opencv-python>=4.9.0.80
Requires-Dist: magnetic_field_calculator>=1.0.2
Requires-Dist: magnetismi>=2022.10.9
Requires-Dist: mpmath>=1.3.0
Requires-Dist: tqdm>=4.66.2
Requires-Dist: lensfunpy>=1.15.0
Requires-Dist: rio_cogeo>=5.3.0
Requires-Dist: fire>=0.7.0
Requires-Dist: scipy>=1.10
Requires-Dist: scikit-image>=0.21
Requires-Dist: scipy>=1.8
Requires-Dist: PyYAML>=6.0.1
Provides-Extra: dev
Requires-Dist: pytest>=7.0.0; extra == "dev"
Requires-Dist: pytest-mock>=3.14.0; extra == "dev"
Requires-Dist: pytest-cov>=4.0.0; extra == "dev"
Requires-Dist: flake8>=6.0.0; extra == "dev"
Requires-Dist: black>=23.0.0; extra == "dev"
Requires-Dist: pre-commit>=4.1.0; extra == "dev"
Requires-Dist: build; extra == "dev"
Dynamic: license-file
